circuits260/__init__.py
circuits260-0.0.1.dist-info/DESCRIPTION.rst
circuits260-0.0.1.dist-info/METADATA
circuits260-0.0.1.dist-info/RECORD
circuits260-0.0.1.dist-info/WHEEL
circuits260-0.0.1.dist-info/metadata.json
circuits260-0.0.1.dist-info/top_level.txt
