Metadata-Version: 2.0
Name: circuits260
Version: 0.0.1
Summary: A Python library consisting of many circuit functions.
Home-page: UNKNOWN
Author: Adrien Carrou
Author-email: adriencarrou@gmail.com
License: MIT
Keywords: circuits
Platform: UNKNOWN
Classifier: Development Status :: 5 - Production/Stable
Classifier: Intended Audience :: Education
Classifier: Operating System :: Microsoft :: Windows :: Windows 10
Classifier: License :: OSI Approved :: MIT License
Classifier: Programming Language :: Python :: 3
Requires-Dist: numpy
